ibm_ai_openscale_cli/VERSION
ibm_ai_openscale_cli/__init__.py
ibm_ai_openscale_cli/api_environment.py
ibm_ai_openscale_cli/credentials.py
ibm_ai_openscale_cli/enums.py
ibm_ai_openscale_cli/environments.py
ibm_ai_openscale_cli/main.py
ibm_ai_openscale_cli/openscale_ops.py
ibm_ai_openscale_cli/ops.py
ibm_ai_openscale_cli/reset_ops.py
ibm_ai_openscale_cli/database_classes/cos.py
ibm_ai_openscale_cli/database_classes/db2.py
ibm_ai_openscale_cli/database_classes/postgres.py
ibm_ai_openscale_cli/database_classes/postgres_compose.py
ibm_ai_openscale_cli/database_classes/postgres_icd.py
ibm_ai_openscale_cli/ml_engines/azure_machine_learning.py
ibm_ai_openscale_cli/ml_engines/custom_machine_learning.py
ibm_ai_openscale_cli/ml_engines/sagemaker_machine_learning.py
ibm_ai_openscale_cli/ml_engines/spss_machine_learning.py
ibm_ai_openscale_cli/ml_engines/watson_machine_learning.py
ibm_ai_openscale_cli/models/model.py
ibm_ai_openscale_cli/models/GermanCreditRiskModel/feedback_data.csv
ibm_ai_openscale_cli/models/GermanCreditRiskModel/history_fairness.json
ibm_ai_openscale_cli/models/GermanCreditRiskModel/history_quality_monitor.json
ibm_ai_openscale_cli/models/GermanCreditRiskModel/training_data.csv
ibm_ai_openscale_cli/models/GermanCreditRiskModel/training_data_statistics.json
ibm_ai_openscale_cli/models/GermanCreditRiskModel/azuremlservice/configuration.json
ibm_ai_openscale_cli/models/GermanCreditRiskModel/azuremlstudio/configuration.json
ibm_ai_openscale_cli/models/GermanCreditRiskModel/azuremlstudio/history_payloads.json
ibm_ai_openscale_cli/models/GermanCreditRiskModel/custom/configuration.json
ibm_ai_openscale_cli/models/GermanCreditRiskModel/custom/history_payloads.json
ibm_ai_openscale_cli/models/GermanCreditRiskModel/sagemaker/configuration.json
ibm_ai_openscale_cli/models/GermanCreditRiskModel/sagemaker/feedback_data.csv
ibm_ai_openscale_cli/models/GermanCreditRiskModel/sagemaker/history_fairness.json
ibm_watson_openscale_cli_tool-3.5.65.dist-info/licenses/LICENSE
ibm_watson_openscale_cli_tool-3.5.65.dist-info/METADATA
ibm_watson_openscale_cli_tool-3.5.65.dist-info/WHEEL
ibm_watson_openscale_cli_tool-3.5.65.dist-info/entry_points.txt
ibm_watson_openscale_cli_tool-3.5.65.dist-info/top_level.txt
ibm_watson_openscale_cli_tool-3.5.65.dist-info/zip-safe
ibm_watson_openscale_cli_tool-3.5.65.dist-info/RECORD
