Metadata-Version: 2.4
Name: ibm-watson-openscale-cli-tool
Version: 3.5.65
Summary: CLI library to automate the onboarding process to IBM Watson OpenScale
Home-page: https://www.ibm.com/cloud/watson-openscale
Author: IBM Corp
Author-email: wps@us.ibm.com
License: Apache-2.0
Keywords: ai-openscale,ibm-watson
Classifier: Programming Language :: Python
Classifier: Programming Language :: Python :: 3
Classifier: Development Status :: 4 - Beta
Classifier: Intended Audience :: Developers
Classifier: Operating System :: OS Independent
Classifier: Topic :: Software Development :: Libraries :: Python Modules
Classifier: Topic :: Software Development :: Libraries :: Application Frameworks
Requires-Python: >=3.10
License-File: LICENSE
Requires-Dist: h5py>=3.11.0
Requires-Dist: requests<3.0,>=2.0
Requires-Dist: urllib3==2.5.0
Requires-Dist: retrying==1.3.4
Requires-Dist: boto3~=1.34.75
Requires-Dist: psycopg2==2.9.9
Requires-Dist: ibm-db>=3.0.3
Requires-Dist: ibm-cloud-sdk-core>=3.16.5
Requires-Dist: ibm-watson-openscale>=3.0.49
Requires-Dist: ibm-watsonx-ai>=1.2.6
Requires-Dist: pandas<2.3.0,>=2.2.0
Requires-Dist: numpy<3.0.0,>=2.0.0
Requires-Dist: pyJWT<3.0.0,>=2.8.0
Requires-Dist: sqlalchemy~=2.0.0
Dynamic: author
Dynamic: author-email
Dynamic: classifier
Dynamic: description
Dynamic: description-content-type
Dynamic: home-page
Dynamic: keywords
Dynamic: license
Dynamic: license-file
Dynamic: requires-dist
Dynamic: requires-python
Dynamic: summary
